setup.py
YanDB/Db.py
YanDB/__init__.py
YanDB.egg-info/PKG-INFO
YanDB.egg-info/SOURCES.txt
YanDB.egg-info/dependency_links.txt
YanDB.egg-info/requires.txt
YanDB.egg-info/top_level.txt